cellproportion/__init__.py
cellproportion/_version.py
cellproportion/core.py
cellproportion/methods.py
cellproportion/spatial.py
cellproportion/utils.py
cellproportion-1.1.1.dist-info/licenses/LICENSE
cellproportion-1.1.1.dist-info/METADATA
cellproportion-1.1.1.dist-info/WHEEL
cellproportion-1.1.1.dist-info/top_level.txt
cellproportion-1.1.1.dist-info/RECORD
