Metadata-Version: 2.4
Name: cellproportion
Version: 1.1.1
Summary: Cell type proportion analysis for single-cell and spatial transcriptomics data
Home-page: https://github.com/ankitpatel/cellproportion
Author: Ankit Patel
Author-email: Ankit Patel <ankit.patel@qmul.ac.uk>
License: MIT
Project-URL: Homepage, https://github.com/ankitpatel/cellproportion
Project-URL: Bug Reports, https://github.com/ankitpatel/cellproportion/issues
Project-URL: Source, https://github.com/ankitpatel/cellproportion
Project-URL: Documentation, https://cellproportion.readthedocs.io/
Keywords: single-cell,spatial-transcriptomics,cell-type-analysis,proportion-analysis,bioinformatics,genomics,scRNA-seq
Classifier: Development Status :: 5 - Production/Stable
Classifier: Intended Audience :: Science/Research
Classifier: Topic :: Scientific/Engineering :: Bio-Informatics
Classifier: License :: OSI Approved :: MIT License
Classifier: Programming Language :: Python :: 3
Classifier: Programming Language :: Python :: 3.8
Classifier: Programming Language :: Python :: 3.9
Classifier: Programming Language :: Python :: 3.10
Classifier: Programming Language :: Python :: 3.11
Classifier: Programming Language :: Python :: 3.12
Classifier: Operating System :: OS Independent
Requires-Python: >=3.8
License-File: LICENSE
Requires-Dist: pandas>=1.3.0
Requires-Dist: numpy>=1.20.0
Requires-Dist: scipy>=1.7.0
Requires-Dist: statsmodels>=0.12.0
Requires-Dist: anndata>=0.8.0
Provides-Extra: dev
Requires-Dist: pytest>=6.0; extra == "dev"
Requires-Dist: pytest-cov; extra == "dev"
Requires-Dist: black; extra == "dev"
Requires-Dist: flake8; extra == "dev"
Requires-Dist: mypy; extra == "dev"
Requires-Dist: sphinx; extra == "dev"
Requires-Dist: sphinx-rtd-theme; extra == "dev"
Dynamic: author
Dynamic: home-page
Dynamic: license-file
Dynamic: requires-python
